MultiGather/Client.py
MultiGather/Types.py
MultiGather/__init__.py
MultiGather-0.0.8.dist-info/METADATA
MultiGather-0.0.8.dist-info/WHEEL
MultiGather-0.0.8.dist-info/top_level.txt
MultiGather-0.0.8.dist-info/RECORD
