Metadata-Version: 2.1
Name: MultiGather
Version: 0.0.8
Summary: Send multiple requests using 3 lines of code!
Author-email: "Mr. Mahdi" <any@hi2.in>
Project-URL: Homepage, https://github.com/tm-sah/MultiGather
Project-URL: Issues, https://github.com/tm-sah/MultiGather/issues
Classifier: Programming Language :: Python :: 3
Classifier: License :: OSI Approved :: MIT License
Classifier: Operating System :: OS Independent
Requires-Python: >=3.8
